cdntools/Kinetics.py
cdntools/MonoSolve.py
cdntools/NetGen.py
cdntools/ReactionSys.py
cdntools/__init__.py
cdntools-0.2.0.dist-info/METADATA
cdntools-0.2.0.dist-info/WHEEL
cdntools-0.2.0.dist-info/licenses/LICENSE
cdntools-0.2.0.dist-info/RECORD
