Metadata-Version: 2.4
Name: cdntools
Version: 0.2.0
Summary: Tools for modeling competitive protein dimerization networks.
License: MIT
License-File: LICENSE
Author: Xiaoyu Wu
Author-email: wuxiaoyu@westlake.edu.cn
Requires-Python: >=3.8
Classifier: Intended Audience :: Science/Research
Classifier: License :: OSI Approved :: MIT License
Classifier: Operating System :: OS Independent
Classifier: Programming Language :: Python :: 3
Classifier: Programming Language :: Python :: 3.8
Classifier: Programming Language :: Python :: 3.9
Classifier: Programming Language :: Python :: 3.10
Classifier: Programming Language :: Python :: 3.11
Classifier: Programming Language :: Python :: 3.12
Classifier: Programming Language :: Python :: 3.13
Classifier: Programming Language :: Python :: 3.14
Provides-Extra: accel
Provides-Extra: plot
Requires-Dist: matplotlib (>=3.5) ; extra == "plot"
Requires-Dist: numba (>=0.56) ; extra == "accel"
Requires-Dist: numpy (>=2.0)
Requires-Dist: scipy (>=1.8)
Project-URL: Documentation, https://github.com/BioProgramming-Lab/CDNtools#readme
Project-URL: Homepage, https://github.com/BioProgramming-Lab/CDNtools
Project-URL: Repository, https://github.com/BioProgramming-Lab/CDNtools
